MANIFEST.in
README.rst
setup.py
collective/__init__.py
collective.examples.userdata.egg-info/PKG-INFO
collective.examples.userdata.egg-info/SOURCES.txt
collective.examples.userdata.egg-info/dependency_links.txt
collective.examples.userdata.egg-info/entry_points.txt
collective.examples.userdata.egg-info/namespace_packages.txt
collective.examples.userdata.egg-info/not-zip-safe
collective.examples.userdata.egg-info/requires.txt
collective.examples.userdata.egg-info/top_level.txt
collective/examples/__init__.py
collective/examples/userdata/__init__.py
collective/examples/userdata/configure.zcml
collective/examples/userdata/interfaces.py
collective/examples/userdata/testing.py
collective/examples/userdata/userdataschema.py
collective/examples/userdata/locales/collective.examples.userdata.pot
collective/examples/userdata/locales/de/LC_MESSAGES/collective.examples.userdata.po
collective/examples/userdata/locales/nl/LC_MESSAGES/collective.examples.userdata.po
collective/examples/userdata/profiles/default/browserlayer.xml
collective/examples/userdata/profiles/default/memberdata_properties.xml
collective/examples/userdata/profiles/default/metadata.xml
collective/examples/userdata/tests/__init__.py
collective/examples/userdata/tests/test_userdataschema.py
docs/HISTORY.txt
docs/INSTALL.txt
docs/LICENSE.GPL
docs/LICENSE.txt
docs/TODO.txt