Metadata-Version: 1.1
Name: collective.examples.userdata
Version: 2.1
Summary: Showcase for the new (Plone 4) plone.app.users IUserDataSchema. Shows how to extend the user data fields that can be selected for the registration form.
Home-page: https://github.com/collective/collective.examples.userdata
Author: Kees Hink
Author-email: plone-developers@lists.sourceforge.net
License: GPL
Platform: UNKNOWN
Classifier: Framework :: Plone
Classifier: Programming Language :: Python
